grpc_registry_protos/__init__.py
grpc_registry_protos/common/__init__.py
grpc_registry_protos/common/common_pb2.py
grpc_registry_protos/common/common_pb2.pyi
grpc_registry_protos/common/common_pb2_grpc.py
grpc_registry_protos/common/common_pb2_grpc.pyi
grpc_registry_protos/common/py.typed
grpc_registry_protos/grand_central/__init__.py
grpc_registry_protos/grand_central/permissions_svc/__init__.py
grpc_registry_protos/grand_central/permissions_svc/permissions_pb2.py
grpc_registry_protos/grand_central/permissions_svc/permissions_pb2.pyi
grpc_registry_protos/grand_central/permissions_svc/permissions_pb2_grpc.py
grpc_registry_protos/grand_central/permissions_svc/permissions_pb2_grpc.pyi
grpc_registry_protos/grand_central/permissions_svc/py.typed
grpc_registry_protos/grand_central/py.typed
grpc_registry_protos/kafka/__init__.py
grpc_registry_protos/kafka/commands_and_events_pb2.py
grpc_registry_protos/kafka/commands_and_events_pb2.pyi
grpc_registry_protos/kafka/commands_and_events_pb2_grpc.py
grpc_registry_protos/kafka/commands_and_events_pb2_grpc.pyi
grpc_registry_protos/kafka/py.typed
grpc_registry_protos/py.typed
grpc_registry_protos/test/__init__.py
grpc_registry_protos/test/py.typed
grpc_registry_protos/test/test_command_pb2.py
grpc_registry_protos/test/test_command_pb2.pyi
grpc_registry_protos/test/test_command_pb2_grpc.py
grpc_registry_protos/test/test_command_pb2_grpc.pyi
grpc_registry_protos/grpc_registry_protos/stubs/py.typed
grpc_registry_protos-0.1.0.dist-info/METADATA
grpc_registry_protos-0.1.0.dist-info/WHEEL
grpc_registry_protos-0.1.0.dist-info/RECORD
